hexonet.apiconnector-4.0.0-py3.10-nspkg.pth
hexonet/apiconnector/__init__.py
hexonet/apiconnector/apiclient.py
hexonet/apiconnector/column.py
hexonet/apiconnector/customlogger.py
hexonet/apiconnector/logger.py
hexonet/apiconnector/record.py
hexonet/apiconnector/response.py
hexonet/apiconnector/responseparser.py
hexonet/apiconnector/responsetemplate.py
hexonet/apiconnector/responsetemplatemanager.py
hexonet/apiconnector/socketconfig.py
hexonet.apiconnector-4.0.0.dist-info/LICENSE
hexonet.apiconnector-4.0.0.dist-info/METADATA
hexonet.apiconnector-4.0.0.dist-info/WHEEL
hexonet.apiconnector-4.0.0.dist-info/dependency_links.txt
hexonet.apiconnector-4.0.0.dist-info/namespace_packages.txt
hexonet.apiconnector-4.0.0.dist-info/top_level.txt
hexonet.apiconnector-4.0.0.dist-info/zip-safe
hexonet.apiconnector-4.0.0.dist-info/RECORD
