Metadata-Version: 2.1
Name: hexonet.apiconnector
Version: 4.0.0
Summary: hexonet.apiconnector is a connector library for the insanely fast HEXONET Backend API
Home-page: https://github.com/hexonet/python-sdk/
Author: Kai Schwarz
Author-email: kschwarz@hexonet.net
Maintainer: Kai Schwarz
Maintainer-email: kschwarz@hexonet.net
License: MIT
Classifier: Programming Language :: Python :: 3
Classifier: License :: OSI Approved :: MIT License
Classifier: Operating System :: OS Independent
License-File: LICENSE
Requires-Dist: docutils (<1,>=0)
Requires-Dist: guzzle-sphinx-theme (<1,>=0)
Requires-Dist: m2r2 (<1,>=0)
Requires-Dist: pytest-cov (<4,>=2)
Requires-Dist: sphinx (<5,>=3)
Requires-Dist: sphinxcontrib-log-cabinet (<2,>=1)
Requires-Dist: sphinxcontrib-websupport (<2,>=1)
Requires-Dist: twine (<5,>=4)
Requires-Dist: black
